sabi-hello-world/__init__.py
utils/__init__.py
utils/myfunc.py
sabi_hello_world-0.2.0.dist-info/LICENSE
sabi_hello_world-0.2.0.dist-info/METADATA
sabi_hello_world-0.2.0.dist-info/WHEEL
sabi_hello_world-0.2.0.dist-info/top_level.txt
sabi_hello_world-0.2.0.dist-info/RECORD
